asyncframe/__init__.py
asyncframe/__main__.py
asyncframe/application.py
asyncframe/auto_migrations.py
asyncframe/background.py
asyncframe/database.py
asyncframe/exceptions.py
asyncframe/fields.py
asyncframe/management.py
asyncframe/middleware.py
asyncframe/migrations.py
asyncframe/models.py
asyncframe/request.py
asyncframe/response.py
asyncframe/routing.py
asyncframe/url.py
asyncframe/views.py
asyncframe/websocket.py
asyncframe-0.1.2.dist-info/licenses/LICENSE
asyncframe-0.1.2.dist-info/METADATA
asyncframe-0.1.2.dist-info/WHEEL
asyncframe-0.1.2.dist-info/entry_points.txt
asyncframe-0.1.2.dist-info/top_level.txt
asyncframe-0.1.2.dist-info/RECORD
