Metadata-Version: 2.4
Name: asyncframe
Version: 0.1.2
Summary: 现代异步Python Web框架，支持FBV和CBV两种编程风格，以及完整的异步ORM系统
Home-page: https://github.com/0716gzs/asyncframe
Author: 0716gzs
Author-email: AsyncFrame Team <team@asyncframe.org>
License: MIT
Project-URL: Homepage, https://github.com/0716gzs/asyncframe
Project-URL: Documentation, https://github.com/0716gzs/asyncframe/blob/main/README.md
Project-URL: Repository, https://github.com/0716gzs/asyncframe.git
Project-URL: Bug Tracker, https://github.com/0716gzs/asyncframe/issues
Keywords: web,framework,async,asyncio,orm,database
Classifier: Development Status :: 4 - Beta
Classifier: Intended Audience :: Developers
Classifier: License :: OSI Approved :: MIT License
Classifier: Programming Language :: Python :: 3
Classifier: Programming Language :: Python :: 3.8
Classifier: Programming Language :: Python :: 3.9
Classifier: Programming Language :: Python :: 3.10
Classifier: Programming Language :: Python :: 3.11
Classifier: Programming Language :: Python :: 3.12
Classifier: Topic :: Internet :: WWW/HTTP :: HTTP Servers
Classifier: Topic :: Internet :: WWW/HTTP :: Dynamic Content
Classifier: Topic :: Software Development :: Libraries :: Python Modules
Classifier: Framework :: AsyncIO
Requires-Python: >=3.8
License-File: LICENSE
Requires-Dist: uvicorn>=0.18.0
Requires-Dist: python-multipart>=0.0.5
Requires-Dist: jinja2>=3.1.0
Requires-Dist: aiofiles>=0.8.0
Requires-Dist: asyncpg>=0.28.0
Requires-Dist: aiomysql>=0.1.1
Requires-Dist: aiosqlite>=0.19.0
Requires-Dist: databases>=0.7.0
Requires-Dist: python-dotenv>=0.19.0
Provides-Extra: dev
Requires-Dist: pytest>=7.0.0; extra == "dev"
Requires-Dist: pytest-asyncio>=0.21.0; extra == "dev"
Requires-Dist: black>=22.0.0; extra == "dev"
Requires-Dist: flake8>=4.0.0; extra == "dev"
Requires-Dist: mypy>=0.991; extra == "dev"
Provides-Extra: mysql
Requires-Dist: aiomysql>=0.1.1; extra == "mysql"
Provides-Extra: postgresql
Requires-Dist: asyncpg>=0.28.0; extra == "postgresql"
Provides-Extra: all
Requires-Dist: aiomysql>=0.1.1; extra == "all"
Requires-Dist: asyncpg>=0.28.0; extra == "all"
Dynamic: author
Dynamic: home-page
Dynamic: license-file
Dynamic: requires-python
